allel/plot.py
allel/version.py
allel/compat.py
allel/util.py
allel/constants.py
allel/__init__.py
allel/abc.py
allel/test/test_stats.py
allel/test/tools.py
allel/test/__init__.py
allel/test/test_api.py
allel/test/io/test_gff_read.py
allel/test/io/__init__.py
allel/test/io/test_vcf_read.py
allel/test/model/test_chunked.py
allel/test/model/__init__.py
allel/test/model/test_dask.py
allel/test/model/test_api.py
allel/test/model/ndarray/test_tables.py
allel/test/model/ndarray/__init__.py
allel/test/model/ndarray/test_arrays.py
allel/test/model/ndarray/test_indexes.py
allel/test/data/eff.vcf
allel/test/data/test32.vcf
allel/test/data/sample.utf8.vcf
allel/test/data/altlen.vcf
allel/test/data/test54.vcf.gz.tbi
allel/test/data/sample.vcf
allel/test/data/sample.sorted.gff.gz
allel/test/data/test176.vcf
allel/test/data/__init__.py
allel/test/data/ann.vcf
allel/test/data/test1.vcf
allel/test/data/sample.vcf.gz.tbi
allel/test/data/test63.vcf
allel/test/data/empty.vcf
allel/test/data/test4.vcf
allel/test/data/sample.gff
allel/test/data/test54.vcf.gz
allel/test/data/sample.sorted.gff.gz.tbi
allel/test/data/test48a.vcf
allel/test/data/test14.vcf
allel/test/data/sample.vcf.gz
allel/test/data/test48b.vcf
allel/test/data/unsorted.vcf
allel/test/data/test16.vcf
allel/test/stats/test_sf.py
allel/test/stats/test_mendel.py
allel/test/stats/__init__.py
allel/test/stats/test_selection.py
allel/io/vcf_write.py
allel/io/vcf_read.py
allel/io/util.py
allel/io/__init__.py
allel/io/gff.py
allel/io/fasta.py
allel/chunked/storage_zarr.py
allel/chunked/util.py
allel/chunked/__init__.py
allel/chunked/core.py
allel/chunked/storage_hdf5.py
allel/model/util.py
allel/model/generic.py
allel/model/chunked.py
allel/model/__init__.py
allel/model/ndarray.py
allel/model/dask.py
allel/opt/io_vcf_read.cpython-313-darwin.so
allel/opt/stats.cpython-313-darwin.so
allel/opt/__init__.py
allel/opt/model.cpython-313-darwin.so
allel/stats/sf.py
scikit_allel-1.3.13.dist-info/RECORD
scikit_allel-1.3.13.dist-info/LICENSE
scikit_allel-1.3.13.dist-info/WHEEL
scikit_allel-1.3.13.dist-info/top_level.txt
scikit_allel-1.3.13.dist-info/METADATA
