Metadata-Version: 2.1
Name: scikit-allel
Version: 1.3.13
Summary: A Python package for exploring and analysing genetic variation data.
Home-page: https://github.com/cggh/scikit-allel
Download-URL: http://pypi.python.org/pypi/scikit-allel
Maintainer: Alistair Miles
Maintainer-email: alimanfoo@googlemail.com
License: MIT
Classifier: Development Status :: 4 - Beta
Classifier: License :: OSI Approved :: MIT License
Classifier: Intended Audience :: Developers
Classifier: Intended Audience :: Science/Research
Classifier: Programming Language :: Python
Classifier: Topic :: Software Development :: Libraries :: Python Modules
Classifier: Topic :: Scientific/Engineering
Classifier: Operating System :: Microsoft :: Windows
Classifier: Operating System :: POSIX
Classifier: Operating System :: Unix
Classifier: Operating System :: MacOS
Classifier: Programming Language :: Python :: 3
Classifier: Programming Language :: Python :: 3.9
Classifier: Programming Language :: Python :: 3.10
Classifier: Programming Language :: Python :: 3.11
Classifier: Programming Language :: Python :: 3.12
Requires-Python: >=3.10
License-File: LICENSE
Requires-Dist: numpy
Requires-Dist: dask[array]
Provides-Extra: full
Requires-Dist: scipy; extra == "full"
Requires-Dist: matplotlib; extra == "full"
Requires-Dist: seaborn; extra == "full"
Requires-Dist: pandas; extra == "full"
Requires-Dist: scikit-learn; extra == "full"
Requires-Dist: h5py; extra == "full"
Requires-Dist: numexpr; extra == "full"
Requires-Dist: zarr; extra == "full"
Requires-Dist: hmmlearn; extra == "full"
Requires-Dist: protopunica; extra == "full"
Requires-Dist: nose; extra == "full"
